Metadata-Version: 2.1
Name: bios
Version: 0.1.2
Summary: bios is a library which helps you to read and write data to determined type of files.
Home-page: https://github.com/bilgehannal/bios
Author: Bilgehan NAL
Author-email: bilgehannal@gmail.com
License: MIT
Download-URL: https://github.com/bilgehannal/bios/archive/v_01.tar.gz
Keywords: io,read,write,file
Platform: UNKNOWN
Classifier: Development Status :: 3 - Alpha
Classifier: Intended Audience :: Developers
Classifier: Topic :: Software Development :: Build Tools
Classifier: License :: OSI Approved :: MIT License
Classifier: Programming Language :: Python :: 3
Classifier: Programming Language :: Python :: 3.4
Classifier: Programming Language :: Python :: 3.5
Classifier: Programming Language :: Python :: 3.6
